scraper_etc/__init__.py
scraper_etc/scraper_etc.py
scraper_etc-0.1.5.dist-info/licenses/LICENSE
scraper_etc-0.1.5.dist-info/METADATA
scraper_etc-0.1.5.dist-info/WHEEL
scraper_etc-0.1.5.dist-info/top_level.txt
scraper_etc-0.1.5.dist-info/RECORD
