Metadata-Version: 2.4
Name: scraper-etc
Version: 0.1.5
Summary: Lightweight utilities for web scraping with requests and Selenium.
Author-email: "E. Tyler Carr" <carret1268@gmail.com>
License: CC0 1.0 Universal (CC0 1.0) Public Domain Dedication
Classifier: Intended Audience :: Developers
Classifier: Topic :: Internet :: WWW/HTTP
Classifier: Topic :: Software Development :: Libraries :: Python Modules
Classifier: Programming Language :: Python
Classifier: Programming Language :: Python :: 3
Classifier: Programming Language :: Python :: 3.10
Classifier: Programming Language :: Python :: 3.11
Classifier: Programming Language :: Python :: 3.12
Classifier: Operating System :: OS Independent
Requires-Python: >=3.10
License-File: LICENSE
Requires-Dist: requests
Requires-Dist: selenium
Requires-Dist: undetected-chromedriver
Dynamic: license-file
